Mega_Bank/OOPS_Prac.py
Mega_Bank/__init__.py
OTT_Platform_Class/__init__.py
OTT_Platform_Class/ott_platform.py
OTT_Platform_Class-0.1.dist-info/License.txt
OTT_Platform_Class-0.1.dist-info/METADATA
OTT_Platform_Class-0.1.dist-info/WHEEL
OTT_Platform_Class-0.1.dist-info/top_level.txt
OTT_Platform_Class-0.1.dist-info/RECORD
