Metadata-Version: 2.1
Name: OTT-Platform-Class
Version: 0.1
Summary: Class package to help us create class User that encapsulate the essential attributes of a user and provide methods that allow a user to interact with the platform.
Author: Minautee
Author-email: minautee.m@fractal.ai
License: MIT
License-File: License.txt
Requires-Dist: pandas
Requires-Dist: requests
